{
  "008000" : {
    "label" : "ResetVector"
  },
  "008034" : {
    "label" : "MainGameLoop"
  },
  "0080b5" : {
    "label" : "JumpToGameMode"
  },
  "0080c6" : {
    "flags" : [ {
      "flagType" : "JmpIndirectLongInterleavedTable",
      "start" : "008061",
      "entries" : 28
    } ]
  },
  "00841e" : {
    "label" : "ClearOam",
    "comment" : "Test3"
  },
  "00879c" : {
    "flags" : [ {
      "flagType" : "NonReturningRoutine"
    } ]
  },
  "0287d0" : {
    "flags" : [ {
      "flagType" : "JslTableRoutine",
      "entries" : 4
    } ]
  },
  "0cc115" : {
    "flags" : [ {
      "flagType" : "JslTableRoutine",
      "entries" : 12
    } ]
  }
}